lammps/.pylintrc.toml
lammps/__init__.py
lammps/binary2txt.exe
lammps/cmake/LAMMPS/LAMMPS_Targets-release.cmake
lammps/cmake/LAMMPS/LAMMPS_Targets.cmake
lammps/cmake/LAMMPS/LAMMPSConfig.cmake
lammps/cmake/LAMMPS/LAMMPSConfigVersion.cmake
lammps/constants.py
lammps/core.py
lammps/data.py
lammps/etc/profile.d/lammps.csh
lammps/etc/profile.d/lammps.sh
lammps/executable.py
lammps/formats.py
lammps/include/lammps/angle.h
lammps/include/lammps/atom.h
lammps/include/lammps/bond.h
lammps/include/lammps/citeme.h
lammps/include/lammps/comm.h
lammps/include/lammps/command.h
lammps/include/lammps/compute.h
lammps/include/lammps/dihedral.h
lammps/include/lammps/domain.h
lammps/include/lammps/error.h
lammps/include/lammps/exceptions.h
lammps/include/lammps/fix.h
lammps/include/lammps/fmt/core.h
lammps/include/lammps/fmt/format.h
lammps/include/lammps/force.h
lammps/include/lammps/group.h
lammps/include/lammps/improper.h
lammps/include/lammps/info.h
lammps/include/lammps/input.h
lammps/include/lammps/kspace.h
lammps/include/lammps/lammps.h
lammps/include/lammps/lattice.h
lammps/include/lammps/library.h
lammps/include/lammps/lmppython.h
lammps/include/lammps/lmptype.h
lammps/include/lammps/memory.h
lammps/include/lammps/modify.h
lammps/include/lammps/neigh_list.h
lammps/include/lammps/neighbor.h
lammps/include/lammps/output.h
lammps/include/lammps/pair.h
lammps/include/lammps/platform.h
lammps/include/lammps/pointers.h
lammps/include/lammps/region.h
lammps/include/lammps/timer.h
lammps/include/lammps/universe.h
lammps/include/lammps/update.h
lammps/include/lammps/utils.h
lammps/include/lammps/variable.h
lammps/ipython/__init__.py
lammps/ipython/magics.py
lammps/ipython/wrapper.py
lammps/lammps.lib
lammps/liblammps.dll
lammps/lmp.exe
lammps/mliap/__init__.py
lammps/mliap/loader.py
lammps/mliap/mliap_unified_abc.py
lammps/mliap/mliap_unified_lj.py
lammps/mliap/pytorch.py
lammps/msi2lmp.exe
lammps/numpy_wrapper.py
lammps/phana.exe
lammps/pkgconfig/liblammps.pc
lammps/pylammps.py
lammps-2025.7.22.2.0.dist-info/METADATA
lammps-2025.7.22.2.0.dist-info/WHEEL
lammps-2025.7.22.2.0.dist-info/entry_points.txt
lammps-2025.7.22.2.0.dist-info/licenses/LICENSE
lammps-2025.7.22.2.0.dist-info/RECORD
